pgthumbor/__init__.py
pgthumbor/models.py
pgthumbor/loaders/__init__.py
pgthumbor/loaders/postgres.py
pgthumbor/storages/__init__.py
pgthumbor/storages/postgres.py
pgthumbor-0.0.9.dist-info/DESCRIPTION.rst
pgthumbor-0.0.9.dist-info/METADATA
pgthumbor-0.0.9.dist-info/RECORD
pgthumbor-0.0.9.dist-info/WHEEL
pgthumbor-0.0.9.dist-info/metadata.json
pgthumbor-0.0.9.dist-info/top_level.txt
